Metadata-Version: 2.1
Name: pyanalyticsgit
Version: 0.5
Summary: Biblioteca PyAnalyticsGit para gerar relatórios Git.
Home-page: UNKNOWN
Author: Jefferson Sena
Author-email: jeffersonsena12144@gmail.com
License: MIT License
Keywords: pyAnalyticsGit
Platform: UNKNOWN
License-File: LICENSE
